WizzPAVal.py
WizzPassVal-1.0.dist-info/LICENSE.txt
WizzPassVal-1.0.dist-info/METADATA
WizzPassVal-1.0.dist-info/WHEEL
WizzPassVal-1.0.dist-info/top_level.txt
WizzPassVal-1.0.dist-info/RECORD
